[
  {
    "source_country": "미국",
    "platform": "Reddit - r/gachagaming",
    "title": "[MONTHLY MEGATHREAD] General Discussion, Simple Questions, Recommendations, and Everything Else - June 2026",
    "content_url": "https://www.reddit.com/r/gachagaming/comments/1ttboxa/monthly_megathread_general_discussion_simple/",
    "timestamp": "2026-06-01 00:01:37",
    "engagement_score": 0,
    "ai_summary": "[미처리] AI 큐레이션 대기 중",
    "translated_full_text": "[미처리] 번역 대기 중",
    "is_hot": false
  },
  {
    "source_country": "미국",
    "platform": "Reddit - r/gachagaming",
    "title": "Wang Yue 2026 New on-site Beta Test Gameplay Showcase (Characters / Pokemon System / Open World)",
    "content_url": "https://www.reddit.com/r/gachagaming/comments/1u9teus/wang_yue_2026_new_onsite_beta_test_gameplay/",
    "timestamp": "2026-06-19 05:39:10",
    "engagement_score": 0,
    "ai_summary": "[미처리] AI 큐레이션 대기 중",
    "translated_full_text": "[미처리] 번역 대기 중",
    "is_hot": false
  },
  {
    "source_country": "미국",
    "platform": "Reddit - r/gachagaming",
    "title": "望月 Wangyue Open World ARPG New Gameplay Demo",
    "content_url": "https://www.reddit.com/r/gachagaming/comments/1u9qnsh/望月_wangyue_open_world_arpg_new_gameplay_demo/",
    "timestamp": "2026-06-19 03:16:05",
    "engagement_score": 0,
    "ai_summary": "[미처리] AI 큐레이션 대기 중",
    "translated_full_text": "[미처리] 번역 대기 중",
    "is_hot": false
  },
  {
    "source_country": "미국",
    "platform": "Reddit - r/gachagaming",
    "title": "Genshin Impact - Snezhnaya Reveal Trailer",
    "content_url": "https://www.reddit.com/r/gachagaming/comments/1u95f45/genshin_impact_snezhnaya_reveal_trailer/",
    "timestamp": "2026-06-18 12:51:56",
    "engagement_score": 0,
    "ai_summary": "드디어 원신 팬들이 그토록 기다려온 마지막 국가, 스네즈나야의 실체가 드러났습니다! 얼음처럼 차갑고 웅장한 설원의 풍경과 함께 우인단 집행관들의 긴장감 넘치는 등장이 시선을 사로잡네요. 과연 여행자는 이 혹독한 추위 속에서 어떤 운명을 맞이하게 될까요? 지금 바로 영상에서 그 압도적인 비주얼을 확인해 보세요!",
    "translated_full_text": "원신 - 스네즈나야 공개 트레일러",
    "is_hot": true
  },
  {
    "source_country": "미국",
    "platform": "Reddit - r/gachagaming",
    "title": "Azur Lane 9th Anniversary 『AZUR LANE MUSI9 FES.』 Event Confirmed!",
    "content_url": "https://www.reddit.com/r/gachagaming/comments/1u9rce9/azur_lane_9th_anniversary_azur_lane_musi9_fes/",
    "timestamp": "2026-06-19 03:50:56",
    "engagement_score": 0,
    "ai_summary": "[미처리] AI 큐레이션 대기 중",
    "translated_full_text": "[미처리] 번역 대기 중",
    "is_hot": false
  },
  {
    "source_country": "미국",
    "platform": "Reddit - r/gachagaming",
    "title": "Wuthering Waves Special Record | Xuanfang",
    "content_url": "https://www.reddit.com/r/gachagaming/comments/1u9qnks/wuthering_waves_special_record_xuanfang/",
    "timestamp": "2026-06-19 03:15:49",
    "engagement_score": 0,
    "ai_summary": "[미처리] AI 큐레이션 대기 중",
    "translated_full_text": "[미처리] 번역 대기 중",
    "is_hot": false
  },
  {
    "source_country": "미국",
    "platform": "Reddit - r/gachagaming",
    "title": "Genshin Impact | Version \"Luna VIII\" \"Sunny Summer Fontinalia\" Trailer",
    "content_url": "https://www.reddit.com/r/gachagaming/comments/1u95av4/genshin_impact_version_luna_viii_sunny_summer/",
    "timestamp": "2026-06-18 12:46:36",
    "engagement_score": 0,
    "ai_summary": "[미처리] AI 큐레이션 대기 중",
    "translated_full_text": "[미처리] 번역 대기 중",
    "is_hot": false
  },
  {
    "source_country": "미국",
    "platform": "Reddit - r/gachagaming",
    "title": "\"Trickcal: Chibi Go\" has started its 0.75th-year celebration event \"Through Time And Space, Just For This Moment\", with a new Eldyne Apostle and Themed Theater, 250 free pulls, and a pet selector that includes the beloved \"Petite Speaki\" pet, among other things.",
    "content_url": "https://www.reddit.com/r/gachagaming/comments/1u91enr/trickcal_chibi_go_has_started_its_075thyear/",
    "timestamp": "2026-06-18 09:17:41",
    "engagement_score": 0,
    "ai_summary": "[미처리] AI 큐레이션 대기 중",
    "translated_full_text": "[미처리] 번역 대기 중",
    "is_hot": false
  },
  {
    "source_country": "미국",
    "platform": "Anime News Network",
    "title": "Live-Action Blue Lock Film Announces 5 More Cast Members",
    "content_url": "https://www.animenewsnetwork.com/news/2026-06-19/live-action-blue-lock-film-announces-5-more-cast-members/.238681",
    "timestamp": "2026-06-19 04:02:48",
    "engagement_score": 0,
    "ai_summary": "[미처리] AI 큐레이션 대기 중",
    "translated_full_text": "[미처리] 번역 대기 중",
    "is_hot": false
  },
  {
    "source_country": "미국",
    "platform": "Anime News Network",
    "title": "Snowball Earth Clashes With Godzilla in Crossover Art",
    "content_url": "https://www.animenewsnetwork.com/interest/2026-06-19/snowball-earth-clashes-with-godzilla-in-crossover-art/.238668",
    "timestamp": "2026-06-19 04:00:00",
    "engagement_score": 0,
    "ai_summary": "[미처리] AI 큐레이션 대기 중",
    "translated_full_text": "[미처리] 번역 대기 중",
    "is_hot": false
  },
  {
    "source_country": "미국",
    "platform": "Anime News Network",
    "title": "Kagurabachi Anime Casts Tomokazu Seki as Kunishige",
    "content_url": "https://www.animenewsnetwork.com/news/2026-06-18/kagurabachi-anime-casts-tomokazu-seki-as-kunishige/.238680",
    "timestamp": "2026-06-19 03:28:46",
    "engagement_score": 0,
    "ai_summary": "[미처리] AI 큐레이션 대기 중",
    "translated_full_text": "[미처리] 번역 대기 중",
    "is_hot": false
  },
  {
    "source_country": "미국",
    "platform": "Anime News Network",
    "title": "Red River Anime's New Video Previews Hiroki Nanami's Opening Song",
    "content_url": "https://www.animenewsnetwork.com/news/2026-06-18/red-river-anime-new-video-previews-hiroki-nanami-opening-song/.238679",
    "timestamp": "2026-06-19 03:20:53",
    "engagement_score": 0,
    "ai_summary": "[미처리] AI 큐레이션 대기 중",
    "translated_full_text": "[미처리] 번역 대기 중",
    "is_hot": false
  },
  {
    "source_country": "미국",
    "platform": "Anime News Network",
    "title": "Cardcaptor Sakura Gets New Smartphone Game on June 25",
    "content_url": "https://www.animenewsnetwork.com/news/2026-06-18/cardcaptor-sakura-gets-new-smartphone-game-on-june-25/.238677",
    "timestamp": "2026-06-19 03:05:45",
    "engagement_score": 0,
    "ai_summary": "[미처리] AI 큐레이션 대기 중",
    "translated_full_text": "[미처리] 번역 대기 중",
    "is_hot": false
  },
  {
    "source_country": "미국",
    "platform": "Anime News Network",
    "title": "Kagami Games to Release My (♂) Life as a Vampire's Maid (♀), 'Please Praise the SR Girls!', Arcana Alchemia, More Games in English",
    "content_url": "https://www.animenewsnetwork.com/news/2026-06-18/kagami-games-to-release-my-life-as-a-vampire-maid-please-praise-the-sr-girls-arcana-alchemia-more-/.238674",
    "timestamp": "2026-06-19 02:30:00",
    "engagement_score": 0,
    "ai_summary": "[미처리] AI 큐레이션 대기 중",
    "translated_full_text": "[미처리] 번역 대기 중",
    "is_hot": false
  },
  {
    "source_country": "미국",
    "platform": "Anime News Network",
    "title": "2026 Crayon Shin-chan Film Casts FRUITS ZIPPER Idols Runa Nakagawa, Noel Hayase",
    "content_url": "https://www.animenewsnetwork.com/news/2026-06-18/2026-crayon-shin-chan-film-casts-fruits-zipper-idols-runa-nakagawa-noel-hayase/.238676",
    "timestamp": "2026-06-19 01:47:15",
    "engagement_score": 0,
    "ai_summary": "[미처리] AI 큐레이션 대기 중",
    "translated_full_text": "[미처리] 번역 대기 중",
    "is_hot": false
  },
  {
    "source_country": "미국",
    "platform": "Anime News Network",
    "title": "Anime Expo 2026 KADOKAWA Booth Exhibit, Merchandise, Panel, and Autograph Session, Details Revealed!",
    "content_url": "https://www.animenewsnetwork.com/press-release/2026-06-18/anime-expo-2026-kadokawa-booth-exhibit-merchandise-panel-and-autograph-session-details-revealed/.238610",
    "timestamp": "2026-06-19 01:00:00",
    "engagement_score": 0,
    "ai_summary": "[미처리] AI 큐레이션 대기 중",
    "translated_full_text": "[미처리] 번역 대기 중",
    "is_hot": false
  },
  {
    "source_country": "미국",
    "platform": "Gematsu (게임 뉴스)",
    "title": "Monochrome Echoes: White coming to Switch this summer",
    "content_url": "https://www.gematsu.com/2026/06/monochrome-echoes-white-coming-to-switch-this-summer",
    "timestamp": "2026-06-19 03:03:08",
    "engagement_score": 0,
    "ai_summary": "[미처리] AI 큐레이션 대기 중",
    "translated_full_text": "[미처리] 번역 대기 중",
    "is_hot": false
  },
  {
    "source_country": "미국",
    "platform": "Gematsu (게임 뉴스)",
    "title": "Persona 4 Revival Broadcast – 22-minute deep dive",
    "content_url": "https://www.gematsu.com/2026/06/persona-4-revival-broadcast-22-minute-deep-dive",
    "timestamp": "2026-06-18 23:54:05",
    "engagement_score": 0,
    "ai_summary": "[미처리] AI 큐레이션 대기 중",
    "translated_full_text": "[미처리] 번역 대기 중",
    "is_hot": false
  },
  {
    "source_country": "미국",
    "platform": "Gematsu (게임 뉴스)",
    "title": "Moonlight Pale adds PS5, Xbox Series, PS4, and Switch versions",
    "content_url": "https://www.gematsu.com/2026/06/moonlight-pale-adds-ps5-xbox-series-ps4-and-switch-versions",
    "timestamp": "2026-06-18 22:28:26",
    "engagement_score": 0,
    "ai_summary": "[미처리] AI 큐레이션 대기 중",
    "translated_full_text": "[미처리] 번역 대기 중",
    "is_hot": false
  },
  {
    "source_country": "미국",
    "platform": "Gematsu (게임 뉴스)",
    "title": "SHINOBI: Art of Vengeance coming to Switch 2 on September 24",
    "content_url": "https://www.gematsu.com/2026/06/shinobi-art-of-vengeance-coming-to-switch-2-on-september-24",
    "timestamp": "2026-06-18 21:30:23",
    "engagement_score": 0,
    "ai_summary": "[미처리] AI 큐레이션 대기 중",
    "translated_full_text": "[미처리] 번역 대기 중",
    "is_hot": false
  },
  {
    "source_country": "미국",
    "platform": "Gematsu (게임 뉴스)",
    "title": "Harvest Moon: Echoes of Teradea debut trailer",
    "content_url": "https://www.gematsu.com/2026/06/harvest-moon-echoes-of-teradea-debut-trailer",
    "timestamp": "2026-06-18 15:24:50",
    "engagement_score": 0,
    "ai_summary": "[미처리] AI 큐레이션 대기 중",
    "translated_full_text": "[미처리] 번역 대기 중",
    "is_hot": false
  },
  {
    "source_country": "미국",
    "platform": "Gematsu (게임 뉴스)",
    "title": "Digimon Story: Time Stranger free update launches July 9, adds Terriermon Assistant, Graphics Mode options, more",
    "content_url": "https://www.gematsu.com/2026/06/digimon-story-time-stranger-free-update-launches-july-9-adds-terriermon-assistant-graphics-mode-options-more",
    "timestamp": "2026-06-18 14:28:06",
    "engagement_score": 0,
    "ai_summary": "[미처리] AI 큐레이션 대기 중",
    "translated_full_text": "[미처리] 번역 대기 중",
    "is_hot": false
  },
  {
    "source_country": "미국",
    "platform": "Gematsu (게임 뉴스)",
    "title": "Gecko Gods coming to Switch 2 on June 25 alongside ‘Forgotten Cove’ update",
    "content_url": "https://www.gematsu.com/2026/06/gecko-gods-coming-to-switch-2-on-june-25-alongside-forgotten-cove-update",
    "timestamp": "2026-06-18 14:16:13",
    "engagement_score": 0,
    "ai_summary": "[미처리] AI 큐레이션 대기 중",
    "translated_full_text": "[미처리] 번역 대기 중",
    "is_hot": false
  },
  {
    "source_country": "미국",
    "platform": "Gematsu (게임 뉴스)",
    "title": "My Hero Academia: All’s Justice coming to Switch 2 on September 3 in Japan, September 4 worldwide",
    "content_url": "https://www.gematsu.com/2026/06/my-hero-academia-alls-justice-coming-to-switch-2-on-september-3-in-japan-september-4-worldwide",
    "timestamp": "2026-06-18 14:05:35",
    "engagement_score": 0,
    "ai_summary": "[미처리] AI 큐레이션 대기 중",
    "translated_full_text": "[미처리] 번역 대기 중",
    "is_hot": false
  },
  {
    "source_country": "일본",
    "platform": "Siliconera (일본겜 특화)",
    "title": "Mead Based on Umamusume Tokai Teio Being Made",
    "content_url": "https://www.siliconera.com/mead-based-on-umamusume-tokai-teio-being-made/",
    "timestamp": "2026-06-19 00:00:12",
    "engagement_score": 0,
    "ai_summary": "[미처리] AI 큐레이션 대기 중",
    "translated_full_text": "[미처리] 번역 대기 중",
    "is_hot": false
  },
  {
    "source_country": "일본",
    "platform": "Siliconera (일본겜 특화)",
    "title": "Naruto Card Game TCG Trailer Appears Ahead of Gen Con 2026",
    "content_url": "https://www.siliconera.com/naruto-card-game-tcg-trailer-appears-ahead-of-gen-con-2026/",
    "timestamp": "2026-06-18 20:00:00",
    "engagement_score": 0,
    "ai_summary": "[미처리] AI 큐레이션 대기 중",
    "translated_full_text": "[미처리] 번역 대기 중",
    "is_hot": false
  },
  {
    "source_country": "일본",
    "platform": "Siliconera (일본겜 특화)",
    "title": "Granblue Fantasy Relink: Endless Ragnarok Demo Debuts",
    "content_url": "https://www.siliconera.com/granblue-fantasy-relink-endless-ragnarok-demo-debuts/",
    "timestamp": "2026-06-18 19:00:00",
    "engagement_score": 0,
    "ai_summary": "[미처리] AI 큐레이션 대기 중",
    "translated_full_text": "[미처리] 번역 대기 중",
    "is_hot": false
  },
  {
    "source_country": "일본",
    "platform": "Siliconera (일본겜 특화)",
    "title": "My Hero Academia: All’s Justice Getting Switch 2 Port",
    "content_url": "https://www.siliconera.com/my-hero-academia-alls-justice-getting-switch-2-port/",
    "timestamp": "2026-06-18 18:00:00",
    "engagement_score": 0,
    "ai_summary": "[미처리] AI 큐레이션 대기 중",
    "translated_full_text": "[미처리] 번역 대기 중",
    "is_hot": false
  },
  {
    "source_country": "일본",
    "platform": "Siliconera (일본겜 특화)",
    "title": "Genshin Impact Luna VIII Adds Sandrone and the Frost Moon",
    "content_url": "https://www.siliconera.com/genshin-impact-luna-viii-adds-sandrone-and-the-frost-moon/",
    "timestamp": "2026-06-18 17:00:00",
    "engagement_score": 0,
    "ai_summary": "[미처리] AI 큐레이션 대기 중",
    "translated_full_text": "[미처리] 번역 대기 중",
    "is_hot": false
  },
  {
    "source_country": "일본",
    "platform": "Siliconera (일본겜 특화)",
    "title": "Pokemon Pokopia Gets a Jirachi Event Next Week",
    "content_url": "https://www.siliconera.com/pokemon-pokopia-gets-a-jirachi-event-next-week/",
    "timestamp": "2026-06-18 16:00:00",
    "engagement_score": 0,
    "ai_summary": "[미처리] AI 큐레이션 대기 중",
    "translated_full_text": "[미처리] 번역 대기 중",
    "is_hot": false
  },
  {
    "source_country": "일본",
    "platform": "Siliconera (일본겜 특화)",
    "title": "New Cardcaptor Sakura Mobile Game Appears Next Week",
    "content_url": "https://www.siliconera.com/new-cardcaptor-sakura-mobile-game-appears-next-week/",
    "timestamp": "2026-06-18 15:00:00",
    "engagement_score": 0,
    "ai_summary": "[미처리] AI 큐레이션 대기 중",
    "translated_full_text": "[미처리] 번역 대기 중",
    "is_hot": false
  },
  {
    "source_country": "일본",
    "platform": "Siliconera (일본겜 특화)",
    "title": "GTA VI Cover Art Appears Ahead of Pre-orders",
    "content_url": "https://www.siliconera.com/gta-vi-cover-art-appears-ahead-of-pre-orders/",
    "timestamp": "2026-06-18 13:50:00",
    "engagement_score": 0,
    "ai_summary": "드디어 GTA 6의 공식 커버 아트가 공개되었습니다! 이번 아트워크는 시리즈 전통의 만화 패널 스타일을 유지하며, 주인공 루시아와 제이슨의 강렬한 모습을 담아냈는데요. 무엇보다 중요한 건 예약 판매 일정입니다. 2026년 6월 25일부터 PS5와 Xbox Series X의 디지털 및 실물 패키지 예약이 시작되니, 한정판을 노리시는 분들은 주요 판매처를 꼭 체크하세요!",
    "translated_full_text": "GTA 6의 사전 예약 소식과 함께 커버 아트가 공개되었습니다. 이번 업데이트에 게임 플레이 영상은 포함되지 않았지만, 락스타 게임즈는 새로운 트레일러를 통해 GTA 6의 커버 아트를 선보였습니다. PS5와 Xbox Series X 버전의 사전 예약은 2026년 6월 25일부터 시작되며, 디지털 및 실물 패키지 모두 해당됩니다. 플레이스테이션 스토어와 마이크로소프트 스토어뿐만 아니라 아마존, 게임스탑 등 주요 소매점에서도 예약이 가능하며, 한정판 출시 가능성도 열려 있습니다. 이번 커버 아트는 기존 시리즈의 전통을 이어받아, 게임 로고를 중심으로 다양한 캐릭터와 이동 수단이 만화 패널 스타일로 배치되었고, 최상단에는 주인공인 루시아 카미노스와 제이슨 듀발이 자리 잡고 있습니다.",
    "is_hot": true
  }
]