[
  {
    "source_country": "미국",
    "platform": "Reddit - r/gachagaming",
    "title": "[MONTHLY MEGATHREAD] General Discussion, Simple Questions, Recommendations, and Everything Else - April 2026",
    "content_url": "https://www.reddit.com/r/gachagaming/comments/1s94jf0/monthly_megathread_general_discussion_simple/",
    "timestamp": "2026-04-01 00:01:08",
    "engagement_score": 0,
    "ai_summary": "[미처리] AI 큐레이션 대기 중",
    "translated_full_text": "[미처리] 번역 대기 중",
    "is_hot": false
  },
  {
    "source_country": "미국",
    "platform": "Reddit - r/gachagaming",
    "title": "Punishing : Gray Raven service expansion notice.",
    "content_url": "https://www.reddit.com/r/gachagaming/comments/1stj5vl/punishing_gray_raven_service_expansion_notice/",
    "timestamp": "2026-04-23 13:43:01",
    "engagement_score": 0,
    "ai_summary": "[미처리] AI 큐레이션 대기 중",
    "translated_full_text": "[미처리] 번역 대기 중",
    "is_hot": false
  },
  {
    "source_country": "미국",
    "platform": "Reddit - r/gachagaming",
    "title": "Neverness to Everness (NTE) has officially begun service in China. Global release in 1 week.",
    "content_url": "https://www.reddit.com/r/gachagaming/comments/1st62ai/neverness_to_everness_nte_has_officially_begun/",
    "timestamp": "2026-04-23 02:34:22",
    "engagement_score": 0,
    "ai_summary": "[미처리] AI 큐레이션 대기 중",
    "translated_full_text": "[미처리] 번역 대기 중",
    "is_hot": false
  },
  {
    "source_country": "미국",
    "platform": "Reddit - r/gachagaming",
    "title": "Astra: Knights of Veda will end its service on June 26, 2026",
    "content_url": "https://www.reddit.com/r/gachagaming/comments/1st9hko/astra_knights_of_veda_will_end_its_service_on/",
    "timestamp": "2026-04-23 05:20:04",
    "engagement_score": 0,
    "ai_summary": "[미처리] AI 큐레이션 대기 중",
    "translated_full_text": "[미처리] 번역 대기 중",
    "is_hot": false
  },
  {
    "source_country": "미국",
    "platform": "Reddit - r/gachagaming",
    "title": "What’s your favorite gacha game song or OST lately?",
    "content_url": "https://www.reddit.com/r/gachagaming/comments/1steov8/whats_your_favorite_gacha_game_song_or_ost_lately/",
    "timestamp": "2026-04-23 10:20:28",
    "engagement_score": 0,
    "ai_summary": "[미처리] AI 큐레이션 대기 중",
    "translated_full_text": "[미처리] 번역 대기 중",
    "is_hot": false
  },
  {
    "source_country": "미국",
    "platform": "Reddit - r/gachagaming",
    "title": "\"Seven Deadly Sins: Grand Cross\" x \"Re Zero\" Collaboration starts tomorrow! 2 free characters! (Rem & Reinhard)",
    "content_url": "https://www.reddit.com/r/gachagaming/comments/1st3kol/seven_deadly_sins_grand_cross_x_re_zero/",
    "timestamp": "2026-04-23 00:41:56",
    "engagement_score": 0,
    "ai_summary": "[미처리] AI 큐레이션 대기 중",
    "translated_full_text": "[미처리] 번역 대기 중",
    "is_hot": false
  },
  {
    "source_country": "미국",
    "platform": "Reddit - r/gachagaming",
    "title": "NIKKE is putting Anis on a Times Square screen for a full day",
    "content_url": "https://www.reddit.com/r/gachagaming/comments/1ss91qu/nikke_is_putting_anis_on_a_times_square_screen/",
    "timestamp": "2026-04-22 02:50:50",
    "engagement_score": 0,
    "ai_summary": "니케의 인기 캐릭터 아니스가 뉴욕 타임스퀘어를 점령합니다! 4월 23일, 24시간 내내 타임스퀘어 대형 전광판에서 아니스를 만나볼 수 있는데요. 매시간 3번씩, 하루 총 72회나 상영된다고 하니 뉴욕에 계신 분들은 꼭 인증샷 남겨야겠네요. 우리 아니스, 이제 월드 스타 다 됐죠?",
    "translated_full_text": "승리의 여신: 니케가 타임스퀘어 전광판에 아니스를 하루 종일 띄웁니다. 4월 23일(미국 동부 시간 기준) 오전 0시부터 24시간 동안 타임스퀘어 전광판에 아니스가 등장할 예정입니다. 해당 영상은 매시간 3회씩, 하루 총 72회 상영됩니다.",
    "is_hot": true
  },
  {
    "source_country": "미국",
    "platform": "Reddit - r/gachagaming",
    "title": "Mongil: Star Dive, A surprisingly fun game, polluted by layers of RNG and Netmarble",
    "content_url": "https://www.reddit.com/r/gachagaming/comments/1ssan4g/mongil_star_dive_a_surprisingly_fun_game_polluted/",
    "timestamp": "2026-04-22 04:04:43",
    "engagement_score": 0,
    "ai_summary": "[미처리] AI 큐레이션 대기 중",
    "translated_full_text": "[미처리] 번역 대기 중",
    "is_hot": false
  },
  {
    "source_country": "미국",
    "platform": "Reddit - r/anime",
    "title": "Anime Questions, Recommendations, and Discussion - April 23, 2026",
    "content_url": "https://www.reddit.com/r/anime/comments/1stecle/anime_questions_recommendations_and_discussion/",
    "timestamp": "2026-04-23 10:01:13",
    "engagement_score": 0,
    "ai_summary": "[미처리] AI 큐레이션 대기 중",
    "translated_full_text": "[미처리] 번역 대기 중",
    "is_hot": false
  },
  {
    "source_country": "미국",
    "platform": "Reddit - r/anime",
    "title": "Meta Thread - Month of April 05, 2026",
    "content_url": "https://www.reddit.com/r/anime/comments/1scormw/meta_thread_month_of_april_05_2026/",
    "timestamp": "2026-04-05 00:00:43",
    "engagement_score": 0,
    "ai_summary": "[미처리] AI 큐레이션 대기 중",
    "translated_full_text": "[미처리] 번역 대기 중",
    "is_hot": false
  },
  {
    "source_country": "미국",
    "platform": "Reddit - r/anime",
    "title": "Chainsaw Man - The Movie: Reze Arc Streams on Crunchyroll Starting April 30",
    "content_url": "https://www.reddit.com/r/anime/comments/1stmycn/chainsaw_man_the_movie_reze_arc_streams_on/",
    "timestamp": "2026-04-23 16:00:49",
    "engagement_score": 0,
    "ai_summary": "드디어 기다리고 기다리던 체인소 맨 극장판, 레제 편의 스트리밍 일정이 공개되었습니다! 오는 4월 30일부터 글로벌 OTT 플랫폼 크런치롤을 통해 만나보실 수 있는데요. 덴지와 레제의 강렬하고도 애틋한 서사가 과연 어떤 작화로 구현되었을지 팬들의 기대감이 최고조에 달하고 있습니다. 놓치지 말고 꼭 체크해 두세요!",
    "translated_full_text": "체인소 맨 - 더 무비: 레제 편, 4월 30일부터 크런치롤에서 스트리밍 시작",
    "is_hot": true
  },
  {
    "source_country": "미국",
    "platform": "Reddit - r/anime",
    "title": "The Ribbon Hero | Anime Movie Announced (Teaser Visual)",
    "content_url": "https://www.reddit.com/r/anime/comments/1stgp97/the_ribbon_hero_anime_movie_announced_teaser/",
    "timestamp": "2026-04-23 12:00:58",
    "engagement_score": 0,
    "ai_summary": "[미처리] AI 큐레이션 대기 중",
    "translated_full_text": "[미처리] 번역 대기 중",
    "is_hot": false
  },
  {
    "source_country": "미국",
    "platform": "Reddit - r/anime",
    "title": "\"The World's Finest Assassin Gets Reincarnated in Another World as an Aristocrat\" Season 2 Teaser Visual",
    "content_url": "https://www.reddit.com/r/anime/comments/1stei71/the_worlds_finest_assassin_gets_reincarnated_in/",
    "timestamp": "2026-04-23 10:10:04",
    "engagement_score": 0,
    "ai_summary": "[미처리] AI 큐레이션 대기 중",
    "translated_full_text": "[미처리] 번역 대기 중",
    "is_hot": false
  },
  {
    "source_country": "미국",
    "platform": "Reddit - r/anime",
    "title": "The Ramparts of Ice • Koori no Jouheki - Episode 4 discussion",
    "content_url": "https://www.reddit.com/r/anime/comments/1stmaxj/the_ramparts_of_ice_koori_no_jouheki_episode_4/",
    "timestamp": "2026-04-23 15:37:31",
    "engagement_score": 0,
    "ai_summary": "[미처리] AI 큐레이션 대기 중",
    "translated_full_text": "[미처리] 번역 대기 중",
    "is_hot": false
  },
  {
    "source_country": "미국",
    "platform": "Reddit - r/anime",
    "title": "Kaho measuring Renako [Watanare ~Next Shine~]",
    "content_url": "https://www.reddit.com/r/anime/comments/1stfe3h/kaho_measuring_renako_watanare_next_shine/",
    "timestamp": "2026-04-23 10:57:40",
    "engagement_score": 0,
    "ai_summary": "[미처리] AI 큐레이션 대기 중",
    "translated_full_text": "[미처리] 번역 대기 중",
    "is_hot": false
  },
  {
    "source_country": "미국",
    "platform": "Reddit - r/anime",
    "title": "Dr. Stone Science Future Part 3 - Episode 4 discussion",
    "content_url": "https://www.reddit.com/r/anime/comments/1stjn13/dr_stone_science_future_part_3_episode_4/",
    "timestamp": "2026-04-23 14:01:35",
    "engagement_score": 0,
    "ai_summary": "[미처리] AI 큐레이션 대기 중",
    "translated_full_text": "[미처리] 번역 대기 중",
    "is_hot": false
  },
  {
    "source_country": "미국",
    "platform": "Reddit - r/gaming",
    "title": "Making Friends Monday! Share your game tags here!",
    "content_url": "https://www.reddit.com/r/gaming/comments/1sqgs2v/making_friends_monday_share_your_game_tags_here/",
    "timestamp": "2026-04-20 06:00:10",
    "engagement_score": 0,
    "ai_summary": "[미처리] AI 큐레이션 대기 중",
    "translated_full_text": "[미처리] 번역 대기 중",
    "is_hot": false
  },
  {
    "source_country": "미국",
    "platform": "Reddit - r/gaming",
    "title": "Microsoft brings Xbox back, scraps Microsoft Gaming",
    "content_url": "https://www.reddit.com/r/gaming/comments/1stpfxv/microsoft_brings_xbox_back_scraps_microsoft_gaming/",
    "timestamp": "2026-04-23 17:28:56",
    "engagement_score": 0,
    "ai_summary": "[미처리] AI 큐레이션 대기 중",
    "translated_full_text": "[미처리] 번역 대기 중",
    "is_hot": false
  },
  {
    "source_country": "미국",
    "platform": "Reddit - r/gaming",
    "title": "Assassin's Creed Black Flag Resynced: Worldwide Reveal Showcase",
    "content_url": "https://www.reddit.com/r/gaming/comments/1stmz1b/assassins_creed_black_flag_resynced_worldwide/",
    "timestamp": "2026-04-23 16:01:26",
    "engagement_score": 0,
    "ai_summary": "[미처리] AI 큐레이션 대기 중",
    "translated_full_text": "[미처리] 번역 대기 중",
    "is_hot": false
  },
  {
    "source_country": "미국",
    "platform": "Reddit - r/gaming",
    "title": "8 years old Conan Exiles is migrating to UE5, it looks great, it's free and it's in less than two weeks. Jesus.",
    "content_url": "https://www.reddit.com/r/gaming/comments/1sto0tq/8_years_old_conan_exiles_is_migrating_to_ue5_it/",
    "timestamp": "2026-04-23 16:39:25",
    "engagement_score": 0,
    "ai_summary": "[미처리] AI 큐레이션 대기 중",
    "translated_full_text": "[미처리] 번역 대기 중",
    "is_hot": false
  },
  {
    "source_country": "미국",
    "platform": "Reddit - r/gaming",
    "title": "As an original early backer of Star Citizen, I have to ask if someone can help: is there actually a realistic roadmap now?",
    "content_url": "https://www.reddit.com/r/gaming/comments/1stf2jq/as_an_original_early_backer_of_star_citizen_i/",
    "timestamp": "2026-04-23 10:40:51",
    "engagement_score": 0,
    "ai_summary": "[미처리] AI 큐레이션 대기 중",
    "translated_full_text": "[미처리] 번역 대기 중",
    "is_hot": false
  },
  {
    "source_country": "미국",
    "platform": "Reddit - r/gaming",
    "title": "Blackbeard was right when he said: \"We'll meet again lad, in this world or the one below\" - AC IV (Resynced)",
    "content_url": "https://www.reddit.com/r/gaming/comments/1stof6k/blackbeard_was_right_when_he_said_well_meet_again/",
    "timestamp": "2026-04-23 16:53:36",
    "engagement_score": 0,
    "ai_summary": "[미처리] AI 큐레이션 대기 중",
    "translated_full_text": "[미처리] 번역 대기 중",
    "is_hot": false
  },
  {
    "source_country": "미국",
    "platform": "Reddit - r/gaming",
    "title": "Nintendo has been sued by two US players who say any tariff refunds it receives from the US government should go back to customers",
    "content_url": "https://www.reddit.com/r/gaming/comments/1ssnzzn/nintendo_has_been_sued_by_two_us_players_who_say/",
    "timestamp": "2026-04-22 14:59:28",
    "engagement_score": 0,
    "ai_summary": "[미처리] AI 큐레이션 대기 중",
    "translated_full_text": "[미처리] 번역 대기 중",
    "is_hot": false
  },
  {
    "source_country": "미국",
    "platform": "Reddit - r/gaming",
    "title": "Some games just never leave your top list, no matter how many years pass. Hard to explain why.",
    "content_url": "https://www.reddit.com/r/gaming/comments/1sthtys/some_games_just_never_leave_your_top_list_no/",
    "timestamp": "2026-04-23 12:49:49",
    "engagement_score": 0,
    "ai_summary": "[미처리] AI 큐레이션 대기 중",
    "translated_full_text": "[미처리] 번역 대기 중",
    "is_hot": false
  },
  {
    "source_country": "미국",
    "platform": "Anime News Network",
    "title": "Crunchyroll Streams 2 The Quintessential Quintuplets Specials",
    "content_url": "https://www.animenewsnetwork.com/news/2026-04-23/crunchyroll-streams-2-the-quintessential-quintuplets-specials/.236719",
    "timestamp": "2026-04-23 18:00:00",
    "engagement_score": 0,
    "ai_summary": "[미처리] AI 큐레이션 대기 중",
    "translated_full_text": "[미처리] 번역 대기 중",
    "is_hot": false
  },
  {
    "source_country": "미국",
    "platform": "Anime News Network",
    "title": "Brigandine: Abyss Strategy Game's Trailer Reveals August 26 Release",
    "content_url": "https://www.animenewsnetwork.com/news/2026-04-23/brigandine-abyss-strategy-game-trailer-reveals-august-26-release/.236728",
    "timestamp": "2026-04-23 17:00:00",
    "engagement_score": 0,
    "ai_summary": "[미처리] AI 큐레이션 대기 중",
    "translated_full_text": "[미처리] 번역 대기 중",
    "is_hot": false
  },
  {
    "source_country": "미국",
    "platform": "Anime News Network",
    "title": "Crunchyroll Streams Chainsaw Man: Reze Arc Anime Film on April 30",
    "content_url": "https://www.animenewsnetwork.com/daily-briefs/2026-04-23/crunchyroll-streams-chainsaw-man-reze-arc-anime-film-on-april-30/.236727",
    "timestamp": "2026-04-23 16:30:00",
    "engagement_score": 0,
    "ai_summary": "[미처리] AI 큐레이션 대기 중",
    "translated_full_text": "[미처리] 번역 대기 중",
    "is_hot": false
  },
  {
    "source_country": "미국",
    "platform": "Anime News Network",
    "title": "Slasher Maidens Manga Enters Irregular Serialization",
    "content_url": "https://www.animenewsnetwork.com/news/2026-04-23/slasher-maidens-manga-enters-irregular-serialization/.236652",
    "timestamp": "2026-04-23 16:15:00",
    "engagement_score": 0,
    "ai_summary": "[미처리] AI 큐레이션 대기 중",
    "translated_full_text": "[미처리] 번역 대기 중",
    "is_hot": false
  },
  {
    "source_country": "미국",
    "platform": "Anime News Network",
    "title": "Dangers in My Heart Volumes 9-12 Manga Review",
    "content_url": "https://www.animenewsnetwork.com/review/dangers-in-my-heart-volumes-9-12-manga/.235036",
    "timestamp": "2026-04-23 16:00:00",
    "engagement_score": 0,
    "ai_summary": "[미처리] AI 큐레이션 대기 중",
    "translated_full_text": "[미처리] 번역 대기 중",
    "is_hot": false
  },
  {
    "source_country": "미국",
    "platform": "Anime News Network",
    "title": "The Warrior Princess and the Barbaric King, Rent-A-Girlfriend Season 5 Anime Reveal English Dub Casts",
    "content_url": "https://www.animenewsnetwork.com/news/2026-04-23/the-warrior-princess-and-the-barbaric-king-rent-a-girlfriend-season-5-anime-reveal-english-dub-casts/.236725",
    "timestamp": "2026-04-23 16:00:00",
    "engagement_score": 0,
    "ai_summary": "[미처리] AI 큐레이션 대기 중",
    "translated_full_text": "[미처리] 번역 대기 중",
    "is_hot": false
  },
  {
    "source_country": "미국",
    "platform": "Anime News Network",
    "title": "Beat-Driven Adventure “Yunyun Syndrome!? Rhythm Psychosis” Launches on PC",
    "content_url": "https://www.animenewsnetwork.com/advertorial/2026-04-23/beat-driven-adventure-yunyun-syndrome-rhythm-psychosis-launches-on-pc/.236689",
    "timestamp": "2026-04-23 15:30:00",
    "engagement_score": 0,
    "ai_summary": "[미처리] AI 큐레이션 대기 중",
    "translated_full_text": "[미처리] 번역 대기 중",
    "is_hot": false
  },
  {
    "source_country": "미국",
    "platform": "Anime News Network",
    "title": "Hidekaz Himaruya's Hetalia World Stars Gangsta Manga Ends",
    "content_url": "https://www.animenewsnetwork.com/news/2026-04-23/hidekaz-himaruya-hetalia-world-stars-gangsta-manga-ends/.236690",
    "timestamp": "2026-04-23 15:15:00",
    "engagement_score": 0,
    "ai_summary": "[미처리] AI 큐레이션 대기 중",
    "translated_full_text": "[미처리] 번역 대기 중",
    "is_hot": false
  },
  {
    "source_country": "미국",
    "platform": "Gematsu (게임 뉴스)",
    "title": "Screenbound ‘Gameplay’ trailer",
    "content_url": "https://www.gematsu.com/2026/04/screenbound-gameplay-trailer",
    "timestamp": "2026-04-23 17:39:27",
    "engagement_score": 0,
    "ai_summary": "[미처리] AI 큐레이션 대기 중",
    "translated_full_text": "[미처리] 번역 대기 중",
    "is_hot": false
  },
  {
    "source_country": "미국",
    "platform": "Gematsu (게임 뉴스)",
    "title": "Golf With Your Friends 2 launches this fall for PS5, Xbox Series, Switch 2, and PC",
    "content_url": "https://www.gematsu.com/2026/04/golf-with-your-friends-2-launches-this-fall-for-ps5-xbox-series-switch-2-and-pc",
    "timestamp": "2026-04-23 17:37:59",
    "engagement_score": 0,
    "ai_summary": "[미처리] AI 큐레이션 대기 중",
    "translated_full_text": "[미처리] 번역 대기 중",
    "is_hot": false
  },
  {
    "source_country": "미국",
    "platform": "Gematsu (게임 뉴스)",
    "title": "SpeedRunners 2: King of Speed launches in July",
    "content_url": "https://www.gematsu.com/2026/04/speedrunners-2-king-of-speed-launches-in-july",
    "timestamp": "2026-04-23 17:37:07",
    "engagement_score": 0,
    "ai_summary": "[미처리] AI 큐레이션 대기 중",
    "translated_full_text": "[미처리] 번역 대기 중",
    "is_hot": false
  },
  {
    "source_country": "미국",
    "platform": "Gematsu (게임 뉴스)",
    "title": "Malagasy folklore-inspired action adventure game Kalanoro announced for PS5, Xbox Series, Switch, and PC",
    "content_url": "https://www.gematsu.com/2026/04/malagasy-folklore-inspired-action-adventure-game-kalanoro-announced-for-ps5-xbox-series-switch-and-pc",
    "timestamp": "2026-04-23 17:35:45",
    "engagement_score": 0,
    "ai_summary": "[미처리] AI 큐레이션 대기 중",
    "translated_full_text": "[미처리] 번역 대기 중",
    "is_hot": false
  },
  {
    "source_country": "미국",
    "platform": "Gematsu (게임 뉴스)",
    "title": "Beastro launches May 21",
    "content_url": "https://www.gematsu.com/2026/04/beastro-launches-may-21",
    "timestamp": "2026-04-23 17:32:52",
    "engagement_score": 0,
    "ai_summary": "[미처리] AI 큐레이션 대기 중",
    "translated_full_text": "[미처리] 번역 대기 중",
    "is_hot": false
  },
  {
    "source_country": "미국",
    "platform": "Gematsu (게임 뉴스)",
    "title": "Deep Dish Dungeon adds Xbox Series version",
    "content_url": "https://www.gematsu.com/2026/04/deep-dish-dungeon-adds-xbox-series-version",
    "timestamp": "2026-04-23 17:30:11",
    "engagement_score": 0,
    "ai_summary": "[미처리] AI 큐레이션 대기 중",
    "translated_full_text": "[미처리] 번역 대기 중",
    "is_hot": false
  },
  {
    "source_country": "미국",
    "platform": "Gematsu (게임 뉴스)",
    "title": "Solo Leveling: ARISE OVERDRIVE for PS5, Xbox Series launches in Q3 2026",
    "content_url": "https://www.gematsu.com/2026/04/solo-leveling-arise-overdrive-for-ps5-xbox-series-launches-in-q3-2026",
    "timestamp": "2026-04-23 17:28:45",
    "engagement_score": 0,
    "ai_summary": "[미처리] AI 큐레이션 대기 중",
    "translated_full_text": "[미처리] 번역 대기 중",
    "is_hot": false
  },
  {
    "source_country": "미국",
    "platform": "Gematsu (게임 뉴스)",
    "title": "Free-to-play party platformer Totopia announced for PS5, Xbox Series, PC, iOS, and Android",
    "content_url": "https://www.gematsu.com/2026/04/free-to-play-party-platformer-totopia-announced-for-ps5-xbox-series-pc-ios-and-android",
    "timestamp": "2026-04-23 17:25:37",
    "engagement_score": 0,
    "ai_summary": "[미처리] AI 큐레이션 대기 중",
    "translated_full_text": "[미처리] 번역 대기 중",
    "is_hot": false
  },
  {
    "source_country": "일본",
    "platform": "Siliconera (일본겜 특화)",
    "title": "Another Yoshi and the Mysterious Book Gameplay Trailer Appears",
    "content_url": "https://www.siliconera.com/another-yoshi-and-the-mysterious-book-gameplay-trailer-appears/?utm_source=rss&utm_medium=rss&utm_campaign=another-yoshi-and-the-mysterious-book-gameplay-trailer-appears",
    "timestamp": "2026-04-23 18:00:00",
    "engagement_score": 0,
    "ai_summary": "[미처리] AI 큐레이션 대기 중",
    "translated_full_text": "[미처리] 번역 대기 중",
    "is_hot": false
  },
  {
    "source_country": "일본",
    "platform": "Siliconera (일본겜 특화)",
    "title": "See Rikku from FFX in Her Dissidia Duellum Final Fantasy Trailer",
    "content_url": "https://www.siliconera.com/see-rikku-from-ffx-in-her-dissidia-duellum-final-fantasy-trailer/?utm_source=rss&utm_medium=rss&utm_campaign=see-rikku-from-ffx-in-her-dissidia-duellum-final-fantasy-trailer",
    "timestamp": "2026-04-23 17:00:00",
    "engagement_score": 0,
    "ai_summary": "[미처리] AI 큐레이션 대기 중",
    "translated_full_text": "[미처리] 번역 대기 중",
    "is_hot": false
  },
  {
    "source_country": "일본",
    "platform": "Siliconera (일본겜 특화)",
    "title": "Stray, To a T, and Wanderstop Heading to Switch 2",
    "content_url": "https://www.siliconera.com/stray-to-a-t-and-wanderstop-heading-to-switch-2/?utm_source=rss&utm_medium=rss&utm_campaign=stray-to-a-t-and-wanderstop-heading-to-switch-2",
    "timestamp": "2026-04-23 16:00:00",
    "engagement_score": 0,
    "ai_summary": "[미처리] AI 큐레이션 대기 중",
    "translated_full_text": "[미처리] 번역 대기 중",
    "is_hot": false
  },
  {
    "source_country": "일본",
    "platform": "Siliconera (일본겜 특화)",
    "title": "Street Fighter 6 Ingrid Release Date Set, Moveset Teased",
    "content_url": "https://www.siliconera.com/street-fighter-6-ingrid-release-date-set-moveset-teased/?utm_source=rss&utm_medium=rss&utm_campaign=street-fighter-6-ingrid-release-date-set-moveset-teased",
    "timestamp": "2026-04-23 15:00:00",
    "engagement_score": 0,
    "ai_summary": "[미처리] AI 큐레이션 대기 중",
    "translated_full_text": "[미처리] 번역 대기 중",
    "is_hot": false
  },
  {
    "source_country": "일본",
    "platform": "Siliconera (일본겜 특화)",
    "title": "Bleach x LAM Soul Art Showcase Announced",
    "content_url": "https://www.siliconera.com/bleach-x-lam-soul-art-showcase-announced/?utm_source=rss&utm_medium=rss&utm_campaign=bleach-x-lam-soul-art-showcase-announced",
    "timestamp": "2026-04-23 14:00:57",
    "engagement_score": 0,
    "ai_summary": "[미처리] AI 큐레이션 대기 중",
    "translated_full_text": "[미처리] 번역 대기 중",
    "is_hot": false
  },
  {
    "source_country": "일본",
    "platform": "Siliconera (일본겜 특화)",
    "title": "Review: I’m so Disappointed in Dissidia Duellum Final Fantasy",
    "content_url": "https://www.siliconera.com/review-im-so-disappointed-in-dissidia-duellum-final-fantasy/?utm_source=rss&utm_medium=rss&utm_campaign=review-im-so-disappointed-in-dissidia-duellum-final-fantasy",
    "timestamp": "2026-04-23 13:00:00",
    "engagement_score": 0,
    "ai_summary": "[미처리] AI 큐레이션 대기 중",
    "translated_full_text": "[미처리] 번역 대기 중",
    "is_hot": false
  },
  {
    "source_country": "일본",
    "platform": "Siliconera (일본겜 특화)",
    "title": "Final Fantasy XIV Manga Chapters Free During 2026 US Fan Fest",
    "content_url": "https://www.siliconera.com/final-fantasy-xiv-manga-chapters-free-during-2026-us-fan-fest/?utm_source=rss&utm_medium=rss&utm_campaign=final-fantasy-xiv-manga-chapters-free-during-2026-us-fan-fest",
    "timestamp": "2026-04-22 21:00:00",
    "engagement_score": 0,
    "ai_summary": "[미처리] AI 큐레이션 대기 중",
    "translated_full_text": "[미처리] 번역 대기 중",
    "is_hot": false
  },
  {
    "source_country": "일본",
    "platform": "Siliconera (일본겜 특화)",
    "title": "Genshin Impact Behind the Scenes Video Covers Snezhnaya",
    "content_url": "https://www.siliconera.com/genshin-impact-behind-the-scenes-video-covers-snezhnaya/?utm_source=rss&utm_medium=rss&utm_campaign=genshin-impact-behind-the-scenes-video-covers-snezhnaya",
    "timestamp": "2026-04-22 20:00:00",
    "engagement_score": 0,
    "ai_summary": "[미처리] AI 큐레이션 대기 중",
    "translated_full_text": "[미처리] 번역 대기 중",
    "is_hot": false
  }
]